LICENSE
MANIFEST.in
README.md
setup.py
src/afaligner/__init__.py
src/afaligner/c_dtwbd_wrapper.py
src/afaligner/dtwbd.py
src/afaligner.egg-info/PKG-INFO
src/afaligner.egg-info/SOURCES.txt
src/afaligner.egg-info/dependency_links.txt
src/afaligner.egg-info/requires.txt
src/afaligner.egg-info/top_level.txt
src/afaligner/c_modules/dtwbd.c
src/afaligner/templates/template.smil
tests/.DS_Store
tests/__init__.py
tests/conftest.py
tests/test_alignment.py
tests/test_dtwbd.py
tests/test_sync_map.py