Metadata-Version: 2.1
Name: afaligner
Version: 0.1.8
Summary: A forced aligner intended for synchronization of narrated text
Home-page: https://github.com/r4victor/afaligner
Author: Victor Skvortsov
Author-email: vds003@gmail.com
License: MIT
Keywords: forced-alignment
Platform: UNKNOWN
Classifier: Topic :: Multimedia :: Sound/Audio :: Speech
Classifier: Development Status :: 3 - Alpha
Classifier: Programming Language :: Python :: 3
Classifier: Programming Language :: C
Classifier: Operating System :: OS Independent
Classifier: License :: OSI Approved :: MIT License
License-File: LICENSE
